{
    "kind": "youtube#playlistItem",
    "id": "UExSY3QxLTVJbi04RXdnNUtxLTBKUDh3aDNad2VPWEg5QS40OEMzNzFDQjA5Q0YxMjQ3",
    "snippet": {
        "publishedAt": "2021-07-03T22:53:25Z",
        "channelId": "UCX5XEfoxcLU9Dr_GVIdsLPA",
        "title": "Alan Walker - Alone",
        "description": "Click the link to listen to my latest album: \nhttps://lnk.to/AlanWalkerWalkerverse\n\nAnd my latest music video, Shut Up with UPSAHL.\nhttps://youtu.be/1sESCIMpx0U\n\n\u25b3 Merch @  https://store.alanwalker.no \u25b3\n\nThanks for listening. \n\n- Alan\n_____________________________\n\nListen to Walkerverse Pt. 1 here:\nhttps://alanwalker.lnk.to/WalkerversePt1\n\nExperience the playlist for Walkerverse Pt. 1 here: https://youtube.com/playlist?list=PLYT4vq6pQVSsPGIkBqrFDux-fKZXSSZ9g\n\n#AlanWalker #Alone #EDM2020 #DownTempo\n_______________________________\n\n// LYRICS // Alan Walker - Alone // LYRICS //\n\nLost in your mind\nI wanna know\nAm I losing my mind?\nNever let me go\n\nIf this night is not forever\nAt least we are together\nI know I'm not alone\nI know I'm not alone\nAnywhere, whenever\nApart, but still together\nI know I'm not alone\nI know I'm not alone\n\nI know I'm not alone\nI know I'm not alone\n\nUnconscious mind\nI'm wide awake\nWanna feel one last time\nTake my pain away\n\nIf this night is not forever\nAt least we are together\nI know I'm not alone\nI know I'm not alone\nAnywhere, whenever\nApart, but still together\nI know I'm not alone\nI know I'm not alone\n\nI know I'm not alone\nI know I'm not alone\nI'm not alone, I'm not alone\nI'm not alone, I know I'm not alone\nI'm not alone, I'm not alone\nI'm not alone, I know I'm not alone\n\n/////////////////////////////////////////\n\nCheck out the restrung LYRIC video for Alone here:\u00a0https://www.youtube.com/watch?v=KMciOb6eU24\n\nAlso, here's the LIVE PERFORMANCE video for Alone, Part II with Ava Max: https://youtu.be/HhjHYkPQ8F0\n\n/////////////////////////////////////////\n\nFacebook: http://bit.ly/AlanWalker_Facebook\nInstagram: http://bit.ly/AlanWalker_Instagram\nTwitter: http://bit.ly/AlanWalker_Twitter\nTiktok: alanwalkermusic\nSnapchat: alanwalkermusic\n\nSubscribe: https://www.youtube.com/user/djwalkzz?sub_confirmation=1\nMake sure to subscribe and ring the bell button to get notifications :) \n\n/////////////////////////////////////////\n\n/// Walker Gaming ///\nWebsite: https://walkergaming.com\u200b\nInstagram: https://www.instagram.com/w47k3rg4m1ng\u200b\nFacebook: https://m.facebook.com/w47k3rg4m1ng\u200b\nTwitch: https://www.twitch.tv/w47k3rg4m1ng\u200b\nTwitter: https://twitter.com/w47k3rg4m1ng\u200b\nTikTok: https://vm.tiktok.com/ZMebouDue\n\n/////////////////////////////////////////\n\nCREDITS\nProduced by: Bror Bror\nDirectors: Rikkard & Tobias H\u00e4ggbom\nConcept by: Lisa Hultengren, Johanna Hoffman & MERD.O.P: Andreas Johannessen & Rikkard H\u00e4ggbom\nProduction Manager: Kristine Planting-Gyllenb\u00e5ga\nProduction assistant: J\u00f8rgen Bertelsen\nDrone crew Bergen: Fredrik Hinsch & Kjetil Fredriksen\nDrone operator Trolltunga: Tor Orset\nAdditional footage: Alexander Zarate Frez\nEditing: Bror Bror\nGrading: Bror \nBrorVFX: Redrow\n\nSpecial thanks to Ulriken643 for their hospitality.\n\nThank you to all the Walkers out there that contributed with footage and as extras in this music video. You are not alone.",
        "thumbnails": {
            "default": {
                "url": "https://i.ytimg.com/vi/1-xGerv5FOk/default.jpg",
                "width": 120,
                "height": 90
            },
            "medium": {
                "url": "https://i.ytimg.com/vi/1-xGerv5FOk/mqdefault.jpg",
                "width": 320,
                "height": 180
            },
            "high": {
                "url": "https://i.ytimg.com/vi/1-xGerv5FOk/hqdefault.jpg",
                "width": 480,
                "height": 360
            },
            "standard": {
                "url": "https://i.ytimg.com/vi/1-xGerv5FOk/sddefault.jpg",
                "width": 640,
                "height": 480
            }
        },
        "channelTitle": "Cyrus Yip",
        "playlistId": "PLRct1-5In-8Ewg5Kq-0JP8wh3ZweOXH9A",
        "resourceId": {
            "kind": "youtube#video",
            "videoId": "1-xGerv5FOk"
        },
        "videoOwnerChannelTitle": "Alan Walker",
        "videoOwnerChannelId": "UCJrOtniJ0-NWz37R30urifQ"
    },
    "contentDetails": {
        "videoId": "1-xGerv5FOk",
        "videoPublishedAt": "2016-12-02T07:59:01Z",
        "duration": "PT2M44S",
        "dimension": "2d",
        "definition": "hd",
        "caption": "false",
        "licensedContent": true,
        "contentRating": {},
        "projection": "rectangular"
    },
    "status": {
        "privacyStatus": "public"
    },
    "statistics": {
        "viewCount": "1314656229",
        "likeCount": "11173068",
        "favoriteCount": "0",
        "commentCount": "415353"
    }
}