{
    "kind": "youtube#playlistItem",
    "id": "UExSY3QxLTVJbi04RXdnNUtxLTBKUDh3aDNad2VPWEg5QS4zM0MzRjA0MDkxNkU2OEUw",
    "snippet": {
        "publishedAt": "2024-05-26T23:19:24Z",
        "channelId": "UCX5XEfoxcLU9Dr_GVIdsLPA",
        "title": "Way Back Home",
        "description": "Provided to YouTube by DCTOM\n\nWay Back Home \u00b7 SHAUN\n\nTake\n\n\u2117 2018 DCTOM\n\nVocals: SHAUN\nWriter: JQ\nWriter: Lee Ji Hye\nWriter: SHAUN\n\nAuto-generated by YouTube.",
        "thumbnails": {
            "default": {
                "url": "https://i.ytimg.com/vi/1rP7ziPDDt0/default.jpg",
                "width": 120,
                "height": 90
            },
            "medium": {
                "url": "https://i.ytimg.com/vi/1rP7ziPDDt0/mqdefault.jpg",
                "width": 320,
                "height": 180
            },
            "high": {
                "url": "https://i.ytimg.com/vi/1rP7ziPDDt0/hqdefault.jpg",
                "width": 480,
                "height": 360
            },
            "standard": {
                "url": "https://i.ytimg.com/vi/1rP7ziPDDt0/sddefault.jpg",
                "width": 640,
                "height": 480
            },
            "maxres": {
                "url": "https://i.ytimg.com/vi/1rP7ziPDDt0/maxresdefault.jpg",
                "width": 1280,
                "height": 720
            }
        },
        "channelTitle": "Cyrus Yip",
        "playlistId": "PLRct1-5In-8Ewg5Kq-0JP8wh3ZweOXH9A",
        "resourceId": {
            "kind": "youtube#video",
            "videoId": "1rP7ziPDDt0"
        },
        "videoOwnerChannelTitle": "SHAUN - Topic",
        "videoOwnerChannelId": "UCZtbCSzIjKOH7lxX8Czo2iw"
    },
    "contentDetails": {
        "videoId": "1rP7ziPDDt0",
        "videoPublishedAt": "2018-06-26T15:01:07Z",
        "duration": "PT3M35S",
        "dimension": "2d",
        "definition": "hd",
        "caption": "false",
        "licensedContent": true,
        "regionRestriction": {
            "allowed": [
                "AE",
                "AR",
                "AT",
                "AU",
                "AW",
                "AZ",
                "BA",
                "BD",
                "BE",
                "BG",
                "BH",
                "BM",
                "BO",
                "BR",
                "BY",
                "CA",
                "CH",
                "CL",
                "CO",
                "CR",
                "CY",
                "CZ",
                "DE",
                "DK",
                "DO",
                "DZ",
                "EC",
                "EE",
                "EG",
                "ES",
                "FI",
                "FR",
                "GB",
                "GE",
                "GF",
                "GH",
                "GP",
                "GR",
                "GT",
                "HK",
                "HN",
                "HR",
                "HU",
                "ID",
                "IE",
                "IL",
                "IN",
                "IQ",
                "IS",
                "IT",
                "JM",
                "JO",
                "JP",
                "KE",
                "KH",
                "KR",
                "KW",
                "KY",
                "KZ",
                "LA",
                "LB",
                "LI",
                "LK",
                "LT",
                "LU",
                "LV",
                "LY",
                "MA",
                "MK",
                "MQ",
                "MT",
                "MX",
                "MY",
                "NC",
                "NG",
                "NI",
                "NL",
                "NO",
                "NP",
                "NZ",
                "OM",
                "PA",
                "PE",
                "PF",
                "PG",
                "PH",
                "PK",
                "PL",
                "PT",
                "PY",
                "QA",
                "RE",
                "RO",
                "RS",
                "RU",
                "SA",
                "SE",
                "SG",
                "SI",
                "SK",
                "SN",
                "SV",
                "TC",
                "TH",
                "TN",
                "TR",
                "TW",
                "TZ",
                "UA",
                "UG",
                "US",
                "UY",
                "VE",
                "VN",
                "YE",
                "YT",
                "ZA",
                "ZW"
            ]
        },
        "contentRating": {},
        "projection": "rectangular"
    },
    "status": {
        "privacyStatus": "public"
    },
    "statistics": {
        "viewCount": "118833824",
        "likeCount": "597727",
        "favoriteCount": "0",
        "commentCount": "1772"
    }
}