{
    "kind": "youtube#playlistItem",
    "id": "UExSY3QxLTVJbi04RXdnNUtxLTBKUDh3aDNad2VPWEg5QS4wMjFBQTlFODBFNjk0NjZB",
    "snippet": {
        "publishedAt": "2022-01-03T07:28:36Z",
        "channelId": "UCX5XEfoxcLU9Dr_GVIdsLPA",
        "title": "\u3010\u81f4\u6211\u4eec\u5355\u7eaf\u7684\u5c0f\u7f8e\u597d\u3011\u4e3b\u9898\u66f2MV\uff1a\u6211\u591a\u559c\u6b22\u4f60\uff0c\u4f60\u4f1a\u77e5\u9053 | I Like You So Much, You\u2019ll Know It | A Love So Beautiful OST Official",
        "description": "A Love So Beautiful: Opening Theme Song - How Much I Like You, You Would Know\n\u2b50\ufe0f\u66f4\u591a\u72ec\u5bb6\u70ed\u5267\u6b22\u8fce\u8ba2\u9605/Subscribe now to watch more dramas\n\u3010\u534e\u7b56\u5f71\u89c6\u5b98\u65b9\u9891\u9053 China Huace TV Official Channel\u3011https://goo.gl/J82VMU\n\u3010\u534e\u7b56\u5f71\u89c6\u9752\u6625\u5267\u573a HUACE GLOBAL FUN\u3011https://goo.gl/wgXP4d\n\n\u25ba\u300a\u81f4\u6211\u4eec\u5355\u7eaf\u7684\u5c0f\u7f8e\u597d\u300b\u5b8c\u6574\u64ad\u653e\u5217\u8868/Full Playlist\uff1ahttps://goo.gl/FMxZy4\n\u25ba\u300a\u81f4\u6211\u4eec\u5355\u7eaf\u7684\u5c0f\u7f8e\u597d\u300b\u7cbe\u5f69\u7247\u6bb5\u53ca\u82b1\u7d6e/Behind the Scenes\uff1ahttps://goo.gl/U7cxRF\n\u25ba\u300a\u81f4\u6211\u4eec\u5355\u7eaf\u7684\u5c0f\u7f8e\u597d\u300bOST Playlist\uff1a https://bit.ly/2RLHwoz\n\n\u25ba\u5267\u96c6\u4fe1\u606f\uff1a\n\u5bfc\u6f14: \u5510\u5f6c / \u6768\u9f99\n\u7f16\u5267: \u5434\u6850 / \u8d75\u4e7e\u4e7e / \u5434\u96ea\u83b9 / \u6bb5\u4f59\u4e50 / \u9c7c\u67af / \u5468\u695a\u5c91 / \u738b\u598d\u84d3\n\u4e3b\u6f14: \u80e1\u4e00\u5929 / \u6c88\u6708 / \u9ad8\u81f3\u9706 / \u738b\u6893\u8587 / \u5b59\u5b81\n\u7c7b\u578b: \u5267\u60c5 / \u7231\u60c5\n\u5236\u7247\u56fd\u5bb6/\u5730\u533a: \u4e2d\u56fd\u5927\u9646\n\u8bed\u8a00: \u6c49\u8bed\u666e\u901a\u8bdd\n\u9996\u64ad: 2017-11-09(\u4e2d\u56fd\u5927\u9646)\n\u96c6\u6570: 24\n\u5355\u96c6\u7247\u957f: 45\u5206\u949f\n\u53c8\u540d: A Love So Beautiful\n\n\u25ba\u5267\u60c5\u7b80\u4ecb\uff1a\n\u6539\u7f16\u81ea\u8d75\u4e7e\u4e7e\u540c\u540d\u7545\u9500\u5c0f\u8bf4\uff0c\u4e3b\u8981\u8bb2\u8ff0\u4e86\u9648\u5c0f\u5e0c\u4e0e\u6c5f\u8fb019\u5e74\u95f4\u5171\u540c\u6210\u957f\uff0c\u4ece\u9752\u6885\u7af9\u9a6c\u5230\u9519\u5931\u540e\u7684\u518d\u6b21\u7275\u624b\u7684\u7231\u60c5\u6545\u4e8b\u3002\u8179\u9ed1\u50b2\u5a07\u7684\u5929\u624d\u533b\u751f\uff0c\u8822\u840c\u9017\u6bd4\u7684\u5143\u6c14\u5c11\u5973\uff0c\u5168\u5267\u6c14\u8d28\u4fcf\u76ae\u5e7d\u9ed8\uff0c\u901a\u8fc7\u5c55\u73b0\u9648\u5c0f\u5e0c\u5012\u8ffd\u6c5f\u8fb0\u4e00\u8def\u4e0a\u557c\u7b11\u7686\u975e\u7684\u65e5\u5e38\uff0c\u8bb0\u5f55\u4e86\u9752\u6625\u65f6\u5149\u91cc\u6700\u7f8e\u597d\u7684\u5fc3\u52a8\u65f6\u523b\uff0c\u5c06\u4e13\u5c5e17\u5c81\u5c11\u7537\u5c11\u5973\u4e4b\u95f4\u7684\u9752\u6da9\u611f\u60c5\u5448\u73b0\u51fa\u6765\uff0c\u5e26\u9886\u89c2\u4f17\u91cd\u8fd4\u597d\u65f6\u5149\u3002\n\n\u25baSynopsis\uff1a\nAdapted from a best-selling novel of the same title written by Zhao Qianqian, the web drama tells the story of how the relationship of Chen Xiaoxi and Jiang Chen changes in 19 years, from breaking up as childhood sweethearts to encountering again as strangers a few years later. A genius doctor with high pride and an 'evil' mind, a pure, energetic and adorkable girl, together they present a hilarious but beautiful romantic teen story. How Chen Xiaoxi chases Jiang Chen may remind the audience of their 17-year-old high school memories.\n\n\u25a0\u25a1\u66f4\u591a\u8ffd\u5267\u4fe1\u606f \u6b22\u8fce\u5173\u6ce8\u534e\u7b56\u793e\u4ea4\u7f51\u7edc\u9875\u9762\u25a0\u25a1\n\u534e\u7b56\u5f71\u89c6Facebook\uff1ahttps://www.facebook.com/huacemedia/\n\u534e\u7b56\u5f71\u89c6Twitter\uff1ahttps://twitter.com/HuaceInfo\n\u534e\u7b56\u5f71\u89c6Instagram\uff1ahttps://www.instagram.com/huace_global/\n\n\u25a0\u25a1\u66f4\u591a\u534e\u7b56\u70ed\u64ad\u5267\u96c6\u25a0\u25a1\n\u5434\u5029&\u5f20\u96e8\u5251\u300a\u6211\u53ea\u559c\u6b22\u4f60\u300bhttps://bit.ly/2VqrAvh\n\u5434\u5029&\u91d1\u6cf0\u7115\u300a\u6211\u7684\u5947\u5999\u7537\u53cb\u300bhttps://goo.gl/2n7rez\nMike Angelo&\u865e\u4e66\u6b23\u300a\u6211\u7684\u5947\u5999\u7537\u53cb2\u300bhttps://bit.ly/2S6DMQ4\n\u9e7f\u6657&\u5173\u6653\u5f64\u300a\u751c\u871c\u66b4\u51fb\u300bhttps://goo.gl/SFsSmu\n\u9ec4\u666f\u745c&\u8bb8\u9b4f\u6d32\u300a\u4e0a\u763e\u300bhttps://goo.gl/q37mYv",
        "thumbnails": {
            "default": {
                "url": "https://i.ytimg.com/vi/7I1SPKwTXJ0/default.jpg",
                "width": 120,
                "height": 90
            },
            "medium": {
                "url": "https://i.ytimg.com/vi/7I1SPKwTXJ0/mqdefault.jpg",
                "width": 320,
                "height": 180
            },
            "high": {
                "url": "https://i.ytimg.com/vi/7I1SPKwTXJ0/hqdefault.jpg",
                "width": 480,
                "height": 360
            },
            "standard": {
                "url": "https://i.ytimg.com/vi/7I1SPKwTXJ0/sddefault.jpg",
                "width": 640,
                "height": 480
            },
            "maxres": {
                "url": "https://i.ytimg.com/vi/7I1SPKwTXJ0/maxresdefault.jpg",
                "width": 1280,
                "height": 720
            }
        },
        "channelTitle": "Cyrus Yip",
        "playlistId": "PLRct1-5In-8Ewg5Kq-0JP8wh3ZweOXH9A",
        "resourceId": {
            "kind": "youtube#video",
            "videoId": "7I1SPKwTXJ0"
        },
        "videoOwnerChannelTitle": "\u534e\u7b56\u5f71\u89c6\u9752\u6625\u5267\u573a HUACE GLOBAL FUN",
        "videoOwnerChannelId": "UC9M9sV3sGmutY26H4LNBTww"
    },
    "contentDetails": {
        "videoId": "7I1SPKwTXJ0",
        "videoPublishedAt": "2017-10-16T03:49:27Z",
        "duration": "PT3M49S",
        "dimension": "2d",
        "definition": "hd",
        "caption": "true",
        "licensedContent": true,
        "contentRating": {},
        "projection": "rectangular"
    },
    "status": {
        "privacyStatus": "public"
    },
    "statistics": {
        "viewCount": "38897279",
        "likeCount": "396251",
        "favoriteCount": "0",
        "commentCount": "9003"
    }
}