{
    "kind": "youtube#playlistItem",
    "id": "UExSY3QxLTVJbi04RXdnNUtxLTBKUDh3aDNad2VPWEg5QS5ENzlGNjFGQzkzQzEzMkNB",
    "snippet": {
        "publishedAt": "2022-07-16T05:34:25Z",
        "channelId": "UCX5XEfoxcLU9Dr_GVIdsLPA",
        "title": "Clash Royale  - Theme Song [TRAP REMIX]",
        "description": "Free for profit, please credit me.",
        "thumbnails": {
            "default": {
                "url": "https://i.ytimg.com/vi/dD-sSMkNvxA/default.jpg",
                "width": 120,
                "height": 90
            },
            "medium": {
                "url": "https://i.ytimg.com/vi/dD-sSMkNvxA/mqdefault.jpg",
                "width": 320,
                "height": 180
            },
            "high": {
                "url": "https://i.ytimg.com/vi/dD-sSMkNvxA/hqdefault.jpg",
                "width": 480,
                "height": 360
            }
        },
        "channelTitle": "Cyrus Yip",
        "playlistId": "PLRct1-5In-8Ewg5Kq-0JP8wh3ZweOXH9A",
        "resourceId": {
            "kind": "youtube#video",
            "videoId": "dD-sSMkNvxA"
        },
        "videoOwnerChannelTitle": "Zomski Beats",
        "videoOwnerChannelId": "UCi6r1Mq8Is-2pr1IGXyMAvQ"
    },
    "contentDetails": {
        "videoId": "dD-sSMkNvxA",
        "videoPublishedAt": "2021-05-15T15:25:04Z",
        "duration": "PT3M14S",
        "dimension": "2d",
        "definition": "hd",
        "caption": "false",
        "licensedContent": false,
        "contentRating": {},
        "projection": "rectangular"
    },
    "status": {
        "privacyStatus": "public"
    },
    "statistics": {
        "viewCount": "183001",
        "likeCount": "5020",
        "favoriteCount": "0",
        "commentCount": "199"
    }
}