{
    "kind": "youtube#playlistItem",
    "id": "UExSY3QxLTVJbi04RXdnNUtxLTBKUDh3aDNad2VPWEg5QS42NEJFMEVGQTYyNTdDQjY0",
    "snippet": {
        "publishedAt": "2022-01-04T05:42:29Z",
        "channelId": "UCX5XEfoxcLU9Dr_GVIdsLPA",
        "title": "I Really Like You, You'll Know It",
        "description": "Provided to YouTube by Studio 71\n\nI Really Like You, You'll Know It \u00b7 jason chen\n\nI Really Like You, You'll Know It\n\n\u2117 2021 jason chen\n\nReleased on: 2021-08-09\n\nAuto-generated by YouTube.",
        "thumbnails": {
            "default": {
                "url": "https://i.ytimg.com/vi/f_S4SD8k-kE/default.jpg",
                "width": 120,
                "height": 90
            },
            "medium": {
                "url": "https://i.ytimg.com/vi/f_S4SD8k-kE/mqdefault.jpg",
                "width": 320,
                "height": 180
            },
            "high": {
                "url": "https://i.ytimg.com/vi/f_S4SD8k-kE/hqdefault.jpg",
                "width": 480,
                "height": 360
            },
            "standard": {
                "url": "https://i.ytimg.com/vi/f_S4SD8k-kE/sddefault.jpg",
                "width": 640,
                "height": 480
            },
            "maxres": {
                "url": "https://i.ytimg.com/vi/f_S4SD8k-kE/maxresdefault.jpg",
                "width": 1280,
                "height": 720
            }
        },
        "channelTitle": "Cyrus Yip",
        "playlistId": "PLRct1-5In-8Ewg5Kq-0JP8wh3ZweOXH9A",
        "resourceId": {
            "kind": "youtube#video",
            "videoId": "f_S4SD8k-kE"
        },
        "videoOwnerChannelTitle": "Jason Chen - Topic",
        "videoOwnerChannelId": "UCoLmFHomrdplbGMj22ixdkA"
    },
    "contentDetails": {
        "videoId": "f_S4SD8k-kE",
        "videoPublishedAt": "2021-08-10T18:12:51Z",
        "duration": "PT3M23S",
        "dimension": "2d",
        "definition": "sd",
        "caption": "false",
        "licensedContent": true,
        "regionRestriction": {
            "allowed": [
                "AE",
                "AR",
                "AS",
                "AT",
                "AU",
                "AW",
                "BA",
                "BE",
                "BG",
                "BH",
                "BM",
                "BO",
                "BR",
                "BY",
                "CA",
                "CH",
                "CL",
                "CO",
                "CR",
                "CY",
                "CZ",
                "DE",
                "DK",
                "DO",
                "DZ",
                "EC",
                "EE",
                "EG",
                "ES",
                "FI",
                "FR",
                "GB",
                "GF",
                "GP",
                "GR",
                "GT",
                "GU",
                "HK",
                "HN",
                "HR",
                "HU",
                "ID",
                "IE",
                "IL",
                "IN",
                "IS",
                "IT",
                "JO",
                "JP",
                "KE",
                "KR",
                "KW",
                "KY",
                "LB",
                "LI",
                "LT",
                "LU",
                "LV",
                "MA",
                "MK",
                "MP",
                "MQ",
                "MT",
                "MX",
                "MY",
                "NC",
                "NG",
                "NI",
                "NL",
                "NO",
                "NZ",
                "OM",
                "PA",
                "PE",
                "PF",
                "PG",
                "PH",
                "PL",
                "PR",
                "PT",
                "PY",
                "QA",
                "RO",
                "RS",
                "RU",
                "SA",
                "SE",
                "SG",
                "SI",
                "SK",
                "SV",
                "TC",
                "TH",
                "TR",
                "TW",
                "UA",
                "US",
                "UY",
                "VE",
                "VI",
                "VN",
                "YT",
                "ZA"
            ]
        },
        "contentRating": {},
        "projection": "rectangular"
    },
    "status": {
        "privacyStatus": "public"
    },
    "statistics": {
        "viewCount": "18941",
        "likeCount": "137",
        "favoriteCount": "0",
        "commentCount": "0"
    }
}