{
    "kind": "youtube#playlistItem",
    "id": "UExSY3QxLTVJbi04RXdnNUtxLTBKUDh3aDNad2VPWEg5QS4yMzk0RjU2NDJBMzI5RDE2",
    "snippet": {
        "publishedAt": "2021-05-25T03:37:12Z",
        "channelId": "UCX5XEfoxcLU9Dr_GVIdsLPA",
        "title": "Hatsune Miku - Turkish March - Owata \\(^o^)/ subbed",
        "description": "song by OwataP\r\n\r\nused video:\r\n\u3010\u521d\u97f3\u30df\u30af\u3011\u30c8\u30eb\u30b3\u884c\u9032\u66f2 - \u30aa\u30ef\u30bf\uff3c(^o^)\uff0f-FULL\u3010PV\u3011\r\nhttp://www.nicovideo.jp/watch/sm3252511\r\n\r\nniconico blog: http://furrball.wordpress.com",
        "thumbnails": {
            "default": {
                "url": "https://i.ytimg.com/vi/fs5_vNMg1xc/default.jpg",
                "width": 120,
                "height": 90
            },
            "medium": {
                "url": "https://i.ytimg.com/vi/fs5_vNMg1xc/mqdefault.jpg",
                "width": 320,
                "height": 180
            },
            "high": {
                "url": "https://i.ytimg.com/vi/fs5_vNMg1xc/hqdefault.jpg",
                "width": 480,
                "height": 360
            }
        },
        "channelTitle": "Cyrus Yip",
        "playlistId": "PLRct1-5In-8Ewg5Kq-0JP8wh3ZweOXH9A",
        "resourceId": {
            "kind": "youtube#video",
            "videoId": "fs5_vNMg1xc"
        },
        "videoOwnerChannelTitle": "nicodances",
        "videoOwnerChannelId": "UCKrH45H3LL4Ke1vtnoPzhgA"
    },
    "contentDetails": {
        "videoId": "fs5_vNMg1xc",
        "videoPublishedAt": "2008-05-11T17:36:33Z",
        "duration": "PT3M7S",
        "dimension": "2d",
        "definition": "sd",
        "caption": "false",
        "licensedContent": false,
        "contentRating": {},
        "projection": "rectangular"
    },
    "status": {
        "privacyStatus": "public"
    },
    "statistics": {
        "viewCount": "246867",
        "likeCount": "3205",
        "favoriteCount": "0",
        "commentCount": "319"
    }
}