{
    "kind": "youtube#playlistItem",
    "id": "UExSY3QxLTVJbi04RXdnNUtxLTBKUDh3aDNad2VPWEg5QS5EODIxMUM1RTNBRUQ3OEU5",
    "snippet": {
        "publishedAt": "2022-08-03T21:22:09Z",
        "channelId": "UCX5XEfoxcLU9Dr_GVIdsLPA",
        "title": "Tate McRae - you're so cool (Lyric Video)",
        "description": "THINK LATER, Tate McRae\u2019s new album, is out now! Listen here: https://tatemcrae.lnk.to/THINKLATER  \n \nShop THINK LATER merchandise, CDs, and more: https://tatemcrae.lnk.to/Store \nThe THINK LATER Tour is coming to a city near you. Find tickets here: https://tatemcrae.com   \n\u2018i used to think i could fly\u2019 out now: https://TateMcRae.lnk.to/iutticf\n\n-----\nFollow Tate: \nInstagram: https://www.instagram.com/tatemcrae/    \nX: https://twitter.com/tatemcrae     \nTikTok: https://www.tiktok.com/@tatemcrae    \nFacebook: https://www.facebook.com/TateMcRaeOfficial/ \nWebsite: https://www.tatemcrae.com/   \nSpotify: https://open.spotify.com/artist/45dkTj5sMRSjrmBSBeiHym?si=NGxzr1LmRH6jDnTW__MNIQ  \n \n#TateMcRae #iusedtothinkicouldfly #pop #youresocool",
        "thumbnails": {
            "default": {
                "url": "https://i.ytimg.com/vi/HanhcnAVZJo/default.jpg",
                "width": 120,
                "height": 90
            },
            "medium": {
                "url": "https://i.ytimg.com/vi/HanhcnAVZJo/mqdefault.jpg",
                "width": 320,
                "height": 180
            },
            "high": {
                "url": "https://i.ytimg.com/vi/HanhcnAVZJo/hqdefault.jpg",
                "width": 480,
                "height": 360
            },
            "standard": {
                "url": "https://i.ytimg.com/vi/HanhcnAVZJo/sddefault.jpg",
                "width": 640,
                "height": 480
            },
            "maxres": {
                "url": "https://i.ytimg.com/vi/HanhcnAVZJo/maxresdefault.jpg",
                "width": 1280,
                "height": 720
            }
        },
        "channelTitle": "Cyrus Yip",
        "playlistId": "PLRct1-5In-8Ewg5Kq-0JP8wh3ZweOXH9A",
        "resourceId": {
            "kind": "youtube#video",
            "videoId": "HanhcnAVZJo"
        },
        "videoOwnerChannelTitle": "TateMcRaeVEVO",
        "videoOwnerChannelId": "UC-yW8iz7ICKv_bhuxLtcJaw"
    },
    "contentDetails": {
        "videoId": "HanhcnAVZJo",
        "videoPublishedAt": "2022-05-27T04:00:06Z",
        "duration": "PT2M51S",
        "dimension": "2d",
        "definition": "hd",
        "caption": "false",
        "licensedContent": true,
        "regionRestriction": {
            "blocked": [
                "RU"
            ]
        },
        "contentRating": {},
        "projection": "rectangular"
    },
    "status": {
        "privacyStatus": "public"
    },
    "statistics": {
        "viewCount": "1544997",
        "likeCount": "26135",
        "favoriteCount": "0",
        "commentCount": "506"
    }
}