{
    "kind": "youtube#playlistItem",
    "id": "UExSY3QxLTVJbi04RXdnNUtxLTBKUDh3aDNad2VPWEg5QS43MkM4NTE4MEJBNkUxODhE",
    "snippet": {
        "publishedAt": "2026-02-02T17:30:10Z",
        "channelId": "UCX5XEfoxcLU9Dr_GVIdsLPA",
        "title": "Stay WITH me",
        "description": "Provided to YouTube by Kakao Entertainment\n\nStay WITH me \u00b7 STAYC \u00b7 Vendors (ZENUR) \u00b7 EL CAPITXN \u00b7 Maria Marcus \u00b7 Vendors (COLL!N) \u00b7 Vendors (Nano) \u00b7 Vendors (ZENUR) \u00b7 \ufeffEL CAPITXN \u00b7 STAYC\n\nMetamorphic\n\n\u2117 2024 High Up Entertainment,under license to Kakao Entertainment\n\nReleased on: 2024-07-01\n\nAuto-generated by YouTube.",
        "thumbnails": {
            "default": {
                "url": "https://i.ytimg.com/vi/kN2s3D5DOhk/default.jpg",
                "width": 120,
                "height": 90
            },
            "medium": {
                "url": "https://i.ytimg.com/vi/kN2s3D5DOhk/mqdefault.jpg",
                "width": 320,
                "height": 180
            },
            "high": {
                "url": "https://i.ytimg.com/vi/kN2s3D5DOhk/hqdefault.jpg",
                "width": 480,
                "height": 360
            },
            "standard": {
                "url": "https://i.ytimg.com/vi/kN2s3D5DOhk/sddefault.jpg",
                "width": 640,
                "height": 480
            },
            "maxres": {
                "url": "https://i.ytimg.com/vi/kN2s3D5DOhk/maxresdefault.jpg",
                "width": 1280,
                "height": 720
            }
        },
        "channelTitle": "Cyrus Yip",
        "playlistId": "PLRct1-5In-8Ewg5Kq-0JP8wh3ZweOXH9A",
        "resourceId": {
            "kind": "youtube#video",
            "videoId": "kN2s3D5DOhk"
        },
        "videoOwnerChannelTitle": "STAYC - Topic",
        "videoOwnerChannelId": "UCwc9eSwp1MAoToS9QUTRpDw"
    },
    "contentDetails": {
        "videoId": "kN2s3D5DOhk",
        "videoPublishedAt": "2024-07-01T09:02:58Z",
        "duration": "PT2M59S",
        "dimension": "2d",
        "definition": "hd",
        "caption": "false",
        "licensedContent": true,
        "contentRating": {},
        "projection": "rectangular"
    },
    "status": {
        "privacyStatus": "public"
    },
    "statistics": {
        "viewCount": "1333713",
        "likeCount": "8841",
        "favoriteCount": "0",
        "commentCount": "253"
    }
}