{
    "kind": "youtube#playlistItem",
    "id": "UExSY3QxLTVJbi04RXdnNUtxLTBKUDh3aDNad2VPWEg5QS41NTZEOThBNThFOUVGQkVB",
    "snippet": {
        "publishedAt": "2021-04-26T01:16:11Z",
        "channelId": "UCX5XEfoxcLU9Dr_GVIdsLPA",
        "title": "Train - Hey, Soul Sister (Official Video)",
        "description": "Train's official music video for 'Hey, Soul Sister' \nListen to Train: https://Train.lnk.to/listenYD\n\nSubscribe to the official Train channel: https://Train.lnk.to/subscribeYD\n\nWatch more of Train\u2019s Music Videos: https://Train.lnk.to/listenYC/youtube\n\nFollow Train:\nFacebook: https://Train.lnk.to/followFI\nTwitter: https://Train.lnk.to/followTI\nInstagram: https://Train.lnk.to/followII\nWebsite: https://Train.lnk.to/followWI\nSpotify: https://Train.lnk.to/followSI\n\n---------\n\nLyrics:\n\n[Intro]\nHeyy\nHe-e-e-e-ey\nHe-e-e-e-ey\n\n[Verse 1]\nYour lipstick stains\nOn the front lobe of my left-side brains\nI knew I wouldn't forget you\nAnd so I went and let you blow my mind\nYour sweet moonbeam\nThe smell of you in every single dream I dream\nI knew when we collided\nYou're the one I have decided who's one of my kind\n\n[Chorus]\nHey, soul sister\nAin't that Mr. Mister on the radio, stereo?\nThe way you move ain't fair, you know\nHey, soul sister\nI don't want to miss a single thing you do\nTonight\n\n[Interlude]\nHeyy\nHe-e-e-e-ey\nHe-e-e-e-ey\n\n[Verse 2]\nJust in time\nI'm so glad you have a one-track mind like me\nYou gave my life direction\nA game show love connection we can't deny\nI'm so obsessed\nMy heart is bound to beat right out my untrimmed chest\nI believe in you, like a virgin you're Madonna\nAnd I'm always gonna wanna blow your mind\n\n[Chorus]\nHey, soul sister\nAin't that Mr. Mister on the radio, stereo?\nThe way you move ain't fair, you know\nHey, soul sister\nI don't want to miss a single thing you do\nTonight\n\n[Bridge]\nThe way you can cut a rug\nWatching you's the only drug I need\nSo gangster, I'm so thug\nYou're the only one I'm dreaming of, you see\nI can be myself now finally\nIn fact there's nothing I can't be\nI want the world to see you be, with me\n\n[Chorus]\nHey, soul sister\nAin't that Mr. Mister on the radio, stereo?\nThe way you move ain't fair, you know\nHey, soul sister\nI don't want to miss a single thing you do tonight\nHey, soul sister\nI don't want to miss a single thing you do\nTonight\n\n#Train #HeySoulSister #AlternativePop",
        "thumbnails": {
            "default": {
                "url": "https://i.ytimg.com/vi/kVpv8-5XWOI/default.jpg",
                "width": 120,
                "height": 90
            },
            "medium": {
                "url": "https://i.ytimg.com/vi/kVpv8-5XWOI/mqdefault.jpg",
                "width": 320,
                "height": 180
            },
            "high": {
                "url": "https://i.ytimg.com/vi/kVpv8-5XWOI/hqdefault.jpg",
                "width": 480,
                "height": 360
            },
            "standard": {
                "url": "https://i.ytimg.com/vi/kVpv8-5XWOI/sddefault.jpg",
                "width": 640,
                "height": 480
            },
            "maxres": {
                "url": "https://i.ytimg.com/vi/kVpv8-5XWOI/maxresdefault.jpg",
                "width": 1280,
                "height": 720
            }
        },
        "channelTitle": "Cyrus Yip",
        "playlistId": "PLRct1-5In-8Ewg5Kq-0JP8wh3ZweOXH9A",
        "resourceId": {
            "kind": "youtube#video",
            "videoId": "kVpv8-5XWOI"
        },
        "videoOwnerChannelTitle": "TrainVEVO",
        "videoOwnerChannelId": "UC5e_2fVZJ2heCb799A04AtA"
    },
    "contentDetails": {
        "videoId": "kVpv8-5XWOI",
        "videoPublishedAt": "2009-11-14T14:32:17Z",
        "duration": "PT3M38S",
        "dimension": "2d",
        "definition": "sd",
        "caption": "true",
        "licensedContent": true,
        "contentRating": {},
        "projection": "rectangular"
    },
    "status": {
        "privacyStatus": "public"
    },
    "statistics": {
        "viewCount": "340230024",
        "likeCount": "2378137",
        "favoriteCount": "0",
        "commentCount": "95943"
    }
}