{
    "kind": "youtube#playlistItem",
    "id": "UExSY3QxLTVJbi04RXdnNUtxLTBKUDh3aDNad2VPWEg5QS4zOEZFNDg4Q0NGM0NBQjlG",
    "snippet": {
        "publishedAt": "2022-10-21T05:56:10Z",
        "channelId": "UCX5XEfoxcLU9Dr_GVIdsLPA",
        "title": "Boys Like You",
        "description": "Provided to YouTube by JYP Entertainment Corporation\n\nBoys Like You \u00b7 ITZY\n\nBoys Like You\n\n\u2117 2022 JYP Entertainment\n\nReleased on: 2022-10-21\n\nMusic  Publisher: The Baron Music Publishing\nMusic  Publisher: The Kennel\nMusic  Publisher: Big Machine Music\nMusic  Publisher: makeumine works\nMusic  Publisher: 153/Joombas Publishing\nLyricist: DIDRIK THOTT\nLyricist: Hayley Aitken\nLyricist: Sara Davis\nLyricist: Ellie Suh(153/Joombas)\nLyricist: \uc774\uc8fc\ud76c(MUMW)\nComposer: DIDRIK THOTT\nComposer: Hayley Aitken\nComposer: SEBASTIAN THOTT\nArranger: SEBASTIAN THOTT\n\nAuto-generated by YouTube.",
        "thumbnails": {
            "default": {
                "url": "https://i.ytimg.com/vi/mjrI9AxEGNY/default.jpg",
                "width": 120,
                "height": 90
            },
            "medium": {
                "url": "https://i.ytimg.com/vi/mjrI9AxEGNY/mqdefault.jpg",
                "width": 320,
                "height": 180
            },
            "high": {
                "url": "https://i.ytimg.com/vi/mjrI9AxEGNY/hqdefault.jpg",
                "width": 480,
                "height": 360
            },
            "standard": {
                "url": "https://i.ytimg.com/vi/mjrI9AxEGNY/sddefault.jpg",
                "width": 640,
                "height": 480
            },
            "maxres": {
                "url": "https://i.ytimg.com/vi/mjrI9AxEGNY/maxresdefault.jpg",
                "width": 1280,
                "height": 720
            }
        },
        "channelTitle": "Cyrus Yip",
        "playlistId": "PLRct1-5In-8Ewg5Kq-0JP8wh3ZweOXH9A",
        "resourceId": {
            "kind": "youtube#video",
            "videoId": "mjrI9AxEGNY"
        },
        "videoOwnerChannelTitle": "ITZY - Topic",
        "videoOwnerChannelId": "UCTP45_DE3fMLujU8sZ-MBzw"
    },
    "contentDetails": {
        "videoId": "mjrI9AxEGNY",
        "videoPublishedAt": "2022-10-21T04:08:32Z",
        "duration": "PT3M44S",
        "dimension": "2d",
        "definition": "hd",
        "caption": "false",
        "licensedContent": true,
        "regionRestriction": {
            "allowed": [
                "AE",
                "AR",
                "AS",
                "AT",
                "AU",
                "AW",
                "BA",
                "BE",
                "BG",
                "BH",
                "BM",
                "BO",
                "BR",
                "BY",
                "CA",
                "CH",
                "CL",
                "CO",
                "CR",
                "CY",
                "CZ",
                "DE",
                "DK",
                "DO",
                "DZ",
                "EC",
                "EE",
                "EG",
                "ES",
                "FI",
                "FR",
                "GB",
                "GF",
                "GP",
                "GR",
                "GT",
                "GU",
                "HK",
                "HN",
                "HR",
                "HU",
                "ID",
                "IE",
                "IL",
                "IN",
                "IS",
                "IT",
                "JO",
                "KE",
                "KR",
                "KW",
                "KY",
                "LB",
                "LI",
                "LT",
                "LU",
                "LV",
                "MA",
                "MK",
                "MP",
                "MQ",
                "MT",
                "MX",
                "MY",
                "NC",
                "NG",
                "NI",
                "NL",
                "NO",
                "NZ",
                "OM",
                "PA",
                "PE",
                "PF",
                "PG",
                "PH",
                "PL",
                "PR",
                "PT",
                "PY",
                "QA",
                "RO",
                "RS",
                "RU",
                "SA",
                "SE",
                "SG",
                "SI",
                "SK",
                "SV",
                "TC",
                "TH",
                "TR",
                "TW",
                "UA",
                "US",
                "UY",
                "VE",
                "VI",
                "VN",
                "YT",
                "ZA"
            ]
        },
        "contentRating": {},
        "projection": "rectangular"
    },
    "status": {
        "privacyStatus": "public"
    },
    "statistics": {
        "viewCount": "2782191",
        "likeCount": "38886",
        "favoriteCount": "0",
        "commentCount": "25"
    }
}