{
    "kind": "youtube#playlistItem",
    "id": "UExSY3QxLTVJbi04RXdnNUtxLTBKUDh3aDNad2VPWEg5QS44RjY1MzU1QjY2QzNFQjE3",
    "snippet": {
        "publishedAt": "2021-11-01T23:09:40Z",
        "channelId": "UCX5XEfoxcLU9Dr_GVIdsLPA",
        "title": "\u3010Vietsub\u3011\u9c7c\u95ea\u95ea\u7ffb\u5531\u963f\u8086\u300a\u70ed\u7231105\u00b0C\u7684\u4f60\u300b\u300eSuper Idol\u7684\u7b11\u5bb9\u4f60\u7684\u751c\u516b\u6b63\u5348\u7684\u9633\u5149\u90fd\u6ca1\u4f60\u8000\u773c\u300f| Ch\u00e0ng Trai Nhi\u1ec7t Huy\u1ebft - Ng\u01b0 Thi\u1ec3m Thi\u1ec3m",
        "description": "#\u70ed\u7231105\u5ea6\u7684\u4f60 #\u963f\u8086 #\u9c7c\u95ea\u95ea\n\n\u3010Vietsub\u3011\u9c7c\u95ea\u95ea\u7ffb\u5531\u963f\u8086\u300a\u70ed\u7231105\u00b0C\u7684\u4f60\u300b\u300eSuper Idol\u7684\u7b11\u5bb9\u4f60\u7684\u751c\u516b\u6b63\u5348\u7684\u9633\u5149\u90fd\u6ca1\u4f60\u8000\u773c\u300f| Ch\u00e0ng Trai Nhi\u1ec7t Huy\u1ebft - Ng\u01b0 Thi\u1ec3m Thi\u1ec3m\n\u00a0\u00a0\u00a0\u00a0\u00a0\u00a0 _______\u00a0 \u2764\ufe0f\u00a0 _______\n\n\u6b4c\u8bcd\uff1a\nSuper Idol\u7684\u7b11\u5bb9\n\u90fd\u6ca1\u4f60\u7684\u751c\n\u516b\u6708\u6b63\u5348\u7684\u9633\u5149\n\u90fd\u6ca1\u4f60\u8000\u773c\n\u70ed\u7231 105 \u00b0C\u7684\u4f60\n\u6ef4\u6ef4\u6e05\u7eaf\u7684\u84b8\u998f\u6c34\n\u4f60\u4e0d\u77e5\u9053\u4f60\u6709\u591a\u53ef\u7231\n\u8dcc\u5012\u540e\u4f1a\u50bb\u7b11\u7740\u518d\u7ad9\u8d77\u6765\n\u4f60\u4ece\u6765\u90fd\u4e0d\u8f7b\u8a00\u5931\u8d25\n\u5bf9\u68a6\u60f3\u7684\u6267\u7740\u4e00\u76f4\u4e0d\u66fe\u66f4\u6539\n\u5f88\u5b89\u5fc3 \u5f53\u4f60\u5bf9\u6211\u8bf4\n\u4e0d\u6015\u6709\u6211\u5728\n\u653e\u7740\u8ba9\u6211\u6765\n\u52c7\u6562\u8ffd\u81ea\u5df1\u7684\u68a6\u60f3\n\u90a3\u575a\u5b9a\u7684\u6a21\u6837\nSuper Idol\u7684\u7b11\u5bb9\n\u90fd\u6ca1\u4f60\u7684\u751c\n\u516b\u6708\u6b63\u5348\u7684\u9633\u5149\n\u90fd\u6ca1\u4f60\u8000\u773c\n\u70ed\u7231 105 \u00b0C\u7684\u4f60\n\u6ef4\u6ef4\u6e05\u7eaf\u7684\u84b8\u998f\u6c34\n\u5728\u8fd9\u72ec\u4e00\u65e0\u4e8c\n\u5c5e\u4e8e\u6211\u7684\u65f6\u4ee3\n\u4e0d\u6015\u5931\u8d25\u6765\u4e00\u573a\n\u75db\u5feb\u7684\u70ed\u7231\n\u70ed\u7231 105\u00b0C\u7684\u4f60\n\u6ef4\u6ef4\u6e05\u7eaf\u7684\u84b8\u998f\u6c34\n\u5728\u8fd9\u72ec\u4e00\u65e0\u4e8c\n\u5c5e\u4e8e\u6211\u7684\u65f6\u4ee3\n\u83ab\u5fd8\u4e86\u521d\u5fc3\u5e38\u5728\n\u75db\u5feb\u53bb\u70ed\u7231\n\u70ed\u7231 105\u00b0C\u7684\u4f60\n\u6ef4\u6ef4\u6e05\u7eaf\u7684\u84b8\u998f\u6c34\n\u559d\u4e00\u53e3\u53c8\u6d3b\u529b\u5168\u5f00\n\u518d\u6b21\u56de\u5230\u6700\u4f73\u72b6\u6001\n\u559d\u4e00\u53e3\u54df\n\u4f60\u4e0d\u77e5\u9053\u4f60\u6709\u591a\u53ef\u7231\n\u8dcc\u5012\u540e\u4f1a\u50bb\u7b11\u7740\u518d\u7ad9\u8d77\u6765\n\u4f60\u4ece\u6765\u90fd\u4e0d\u8f7b\u8a00\u5931\u8d25\n\u5bf9\u68a6\u60f3\u7684\u6267\u7740\u4e00\u76f4\u4e0d\u66fe\u66f4\u6539\n\u5f88\u5b89\u5fc3 \u5f53\u4f60\u5bf9\u6211\u8bf4\n\u4e0d\u6015\u6709\u6211\u5728\n\u653e\u7740\u8ba9\u6211\u6765\n\u52c7\u6562\u8ffd\u81ea\u5df1\u7684\u68a6\u60f3\n\u90a3\u575a\u5b9a\u7684\u6a21\u6837\nSuper Idol\u7684\u7b11\u5bb9\n\u90fd\u6ca1\u4f60\u7684\u751c\n\u516b\u6708\u6b63\u5348\u7684\u9633\u5149\n\u90fd\u6ca1\u4f60\u8000\u773c\n\u70ed\u7231 105\u00b0C\u7684\u4f60\n\u6ef4\u6ef4\u6e05\u7eaf\u7684\u84b8\u998f\u6c34\n\u5728\u8fd9\u72ec\u4e00\u65e0\u4e8c\n\u5c5e\u4e8e\u6211\u7684\u65f6\u4ee3\n\u4e0d\u6015\u5931\u8d25\u6765\u4e00\u573a\n\u75db\u5feb\u7684\u70ed\u7231\n\u70ed\u7231 105\u00b0C\u7684\u4f60\n\u6ef4\u6ef4\u6e05\u7eaf\u7684\u84b8\u998f\u6c34\n\u5728\u8fd9\u72ec\u4e00\u65e0\u4e8c\n\u5c5e\u4e8e\u6211\u7684\u65f6\u4ee3\n\u83ab\u5fd8\u4e86\u521d\u5fc3\u5e38\u5728\n\u75db\u5feb\u53bb\u70ed\u7231\n\u70ed\u7231 105\u00b0C\u7684\u4f60\n\u6ef4\u6ef4\u6e05\u7eaf\u7684\u84b8\u998f\u6c34\n\u559d\u4e00\u53e3\u53c8\u6d3b\u529b\u5168\u5f00\n\u518d\u6b21\u56de\u5230\u6700\u4f73\u72b6\u6001\n\u559d\u4e00\u53e3\u53c8\u6d3b\u529b\u5168\u5f00\n\n\u00a0\u00a0\u00a0\u00a0\u00a0\u00a0 _______\u00a0 \u2764\ufe0f\u00a0 _______\n\n\ud83c\udf1f\u6296\u97f3\u7cbe\u9078\u7ffb\u5531\u7cfb\u5217\uff1a\n\ud83d\udc49 https://youtube.com/playlist?list=PL3UJlIVikfo9JjHwLm3tOGghifJgqnnG-\n\n\ud83c\udf1f\u4e2a\u4eba\u7ffb\u5531\u5408\u96c6\u7cfb\u5217\uff1a\n\n\ud83d\udc49\u738b\u7389\u840c\uff1ahttps://youtube.com/playlist?list=PL3UJlIVikfo84ZS52Ntt_2kJjXzO3P-3Z\n\n\ud83d\udc49\u80d6\u864e\uff1ahttps://youtube.com/playlist?list=PL3UJlIVikfo9R3DhIaVsJHVYwE5-KcoAr\n\n\ud83d\udc49\u9c7c\u95ea\u95eaBLING\uff1ahttps://youtube.com/playlist?list=PL3UJlIVikfo-N7jpK7dXyfkA4m3uSYgZL\n\n\ud83d\udc49\u996d\u601d\u601d\uff1ahttps://youtube.com/playlist?list=PL3UJlIVikfo8-BNztllE0L0vvle3ZRK0H\n\n\ud83d\udc49\u4e03\u5915\uff1ahttps://youtube.com/playlist?list=PL3UJlIVikfo9oeJjklPtaw_gpHIE5IjMq\n\n\ud83d\udc49\u5927\u95e8E\uff1ahttps://youtube.com/playlist?list=PL3UJlIVikfo_rVbf8JQ0g2yxV9nrtNz8e\n\n\ud83d\udc49\u6731\u5bb9\u541b-\u5154\u5b50\u7259\uff1ahttps://youtube.com/playlist?list=PL3UJlIVikfo-_nLFch8dhOiv2U5CU5jzW\n\n\ud83d\udc49\u91ce\u5c0f\u9a6c\uff1ahttps://youtube.com/playlist?list=PL3UJlIVikfo9N6la-Ru7B6pb791Q4FsP9\n\n\ud83d\udc49\u5c0f\u4e09\u91d1\uff1ahttps://youtube.com/playlist?list=PL3UJlIVikfo-kAHfYyJxgin46zjTDbqrw\n\n\ud83d\udc49\u6234\u7fbd\u5f64\uff1ahttps://youtube.com/playlist?list=PL3UJlIVikfo-vYxyLQqQldm2nSe0O_cSp\n\n\ud83d\udc49\u53cc\u5c0f\u5431\uff1ahttps://youtube.com/playlist?list=PL3UJlIVikfo9al3L-otfwxnSGY4bjcTMD\n\n\ud83d\udc49\u6708\u72f8li\uff1ahttps://youtube.com/playlist?list=PL3UJlIVikfo_yWZhT3e_NrJvi9-q85BDB\n\n\ud83d\udc49\u5434\u5cb1\u6797\uff1ahttps://youtube.com/playlist?list=PL3UJlIVikfo9x3idhVNxnm9F-qGRmJ0Ly\n\n\ud83d\udc49\u4e03\u53d4\uff1ahttps://youtube.com/playlist?list=PL3UJlIVikfo8-e-JMuw81--_ySB8Zxr8B\n\nPlease don't reup my video. Thank you!\u2764\ufe0f",
        "thumbnails": {
            "default": {
                "url": "https://i.ytimg.com/vi/PFPtWInnYzw/default.jpg",
                "width": 120,
                "height": 90
            },
            "medium": {
                "url": "https://i.ytimg.com/vi/PFPtWInnYzw/mqdefault.jpg",
                "width": 320,
                "height": 180
            },
            "high": {
                "url": "https://i.ytimg.com/vi/PFPtWInnYzw/hqdefault.jpg",
                "width": 480,
                "height": 360
            },
            "standard": {
                "url": "https://i.ytimg.com/vi/PFPtWInnYzw/sddefault.jpg",
                "width": 640,
                "height": 480
            },
            "maxres": {
                "url": "https://i.ytimg.com/vi/PFPtWInnYzw/maxresdefault.jpg",
                "width": 1280,
                "height": 720
            }
        },
        "channelTitle": "Cyrus Yip",
        "playlistId": "PLRct1-5In-8Ewg5Kq-0JP8wh3ZweOXH9A",
        "resourceId": {
            "kind": "youtube#video",
            "videoId": "PFPtWInnYzw"
        },
        "videoOwnerChannelTitle": "\u738b\u6653\u82f1",
        "videoOwnerChannelId": "UCMq_MrKfv3raj79DqmDItBQ"
    },
    "contentDetails": {
        "videoId": "PFPtWInnYzw",
        "videoPublishedAt": "2021-08-31T11:33:15Z",
        "duration": "PT3M12S",
        "dimension": "2d",
        "definition": "hd",
        "caption": "false",
        "licensedContent": false,
        "contentRating": {},
        "projection": "rectangular"
    },
    "status": {
        "privacyStatus": "public"
    },
    "statistics": {
        "viewCount": "748598",
        "likeCount": "12477",
        "favoriteCount": "0",
        "commentCount": "479"
    }
}