{
    "kind": "youtube#playlistItem",
    "id": "UExSY3QxLTVJbi04RXdnNUtxLTBKUDh3aDNad2VPWEg5QS43NkI3M0NGOUE4ODY2OTE1",
    "snippet": {
        "publishedAt": "2021-07-03T22:24:05Z",
        "channelId": "UCX5XEfoxcLU9Dr_GVIdsLPA",
        "title": "Seishun Buta Yarou wa Bunny Girl Senpai no Yume wo Minai ED - \"Fukashigi no Carte\" (Piano)",
        "description": "\u2771 SUBSCRIBE FOR MORE QUALITY MUSIC!!!\nhttp://bit.ly/SubscribeFonziYT\n\n\u2771 Support the channel by becoming a member!!! Join here:\nhttps://www.youtube.com/user/FonziMGM/join\n\n\u2771 Anime Piano Music on Spotify: https://spoti.fi/2VMGV5f\n\n\u2771 Learn piano easily: https://go.flowkey.com/fonzi *\n\n----------------------------------------\u00ad\u00ad-----\n\u2771 Support me and my music FOR FREE by listening to my covers on Spotify: http://spoti.fi/2hvpt67  \n\nDownload my covers on...\n\u2771 iTunes: http://apple.co/2ipCye1\n\u2771 Google Play: http://bit.ly/GooglePlayFonzi\n\u2771 Amazon: http://amzn.to/2i6eNd7\n\n\u25cf FACEBOOK: http://www.facebook.com/fonzimgm\n\u25cf TWITTER: https://twitter.com/FonziMGM\n\n------------------------------------------\nHey guys,\nHere is my arrangement of Fukashigi no Carte! \n\nAnd as always, enjoy!\n\nSong Title: Fukashigi no Carte\nOriginal Artist: Mai Sakurajima (Asami Seto), Tomoe Koga (Nao Touyama), Rio Futaba (Atsumi Tanezaki), Nodoka Toyohama (Maaya Uchida), Kaede Azusawara (Yurika Kubo), Shouko Makinohara (Inori Minase)\n\n-------------------------------------------\n\u25cf Download my MIDI files through Patreon: http://www.patreon.com/fonzi\n\n\u266b Sheet Music (Full Song): https://www.mymusicsheet.com/FonziMGM/25658\nThe first 2 pages are basically the TV-size / this video (sheets are 99% identical to this video with a few minor changes to try and make it more faithful to the original song)\n\n\u266b Download the sheet music for my covers here: https://www.mymusicsheet.com/FonziMGM\n*Due to copyright reasons, all sheet music for Fonzi M's piano covers on this website are distributed for a fee. Thank you for understanding.\n\n#SeishunButaYarouwaBunnyGirlSenpainoYumewoMinai #FukashigiNoCarte #PianoCover #BunnyGirlAnime #BunnyGirlSenpaiED #BunnyGirlSenpaiThemeSong\n-------------------------------------------\n*Affiliate link",
        "thumbnails": {
            "default": {
                "url": "https://i.ytimg.com/vi/PIL8I32Ko2A/default.jpg",
                "width": 120,
                "height": 90
            },
            "medium": {
                "url": "https://i.ytimg.com/vi/PIL8I32Ko2A/mqdefault.jpg",
                "width": 320,
                "height": 180
            },
            "high": {
                "url": "https://i.ytimg.com/vi/PIL8I32Ko2A/hqdefault.jpg",
                "width": 480,
                "height": 360
            },
            "standard": {
                "url": "https://i.ytimg.com/vi/PIL8I32Ko2A/sddefault.jpg",
                "width": 640,
                "height": 480
            },
            "maxres": {
                "url": "https://i.ytimg.com/vi/PIL8I32Ko2A/maxresdefault.jpg",
                "width": 1280,
                "height": 720
            }
        },
        "channelTitle": "Cyrus Yip",
        "playlistId": "PLRct1-5In-8Ewg5Kq-0JP8wh3ZweOXH9A",
        "resourceId": {
            "kind": "youtube#video",
            "videoId": "PIL8I32Ko2A"
        },
        "videoOwnerChannelTitle": "Fonzi M - Melodies on Piano",
        "videoOwnerChannelId": "UCpQUBJrRfcpWLro4Oziff7Q"
    },
    "contentDetails": {
        "videoId": "PIL8I32Ko2A",
        "videoPublishedAt": "2018-10-03T14:30:00Z",
        "duration": "PT1M58S",
        "dimension": "2d",
        "definition": "hd",
        "caption": "false",
        "licensedContent": false,
        "contentRating": {},
        "projection": "rectangular"
    },
    "status": {
        "privacyStatus": "public"
    },
    "statistics": {
        "viewCount": "2570977",
        "likeCount": "84637",
        "favoriteCount": "0",
        "commentCount": "1540"
    }
}