{
    "kind": "youtube#playlistItem",
    "id": "UExSY3QxLTVJbi04RXdnNUtxLTBKUDh3aDNad2VPWEg5QS5EMDk3NkYyMTM0MUIxN0ZG",
    "snippet": {
        "publishedAt": "2022-07-25T21:48:37Z",
        "channelId": "UCX5XEfoxcLU9Dr_GVIdsLPA",
        "title": "Steve Burns - Mighty Little Man (Official Audio)",
        "description": "Spotify: https://open.spotify.com/track/3apMgueqUAjmm1yTRF21Il\nApple Music: https://itunes.apple.com/gb/album/mighty-little-man-single/id1272862750",
        "thumbnails": {
            "default": {
                "url": "https://i.ytimg.com/vi/SeVIyZaY_C0/default.jpg",
                "width": 120,
                "height": 90
            },
            "medium": {
                "url": "https://i.ytimg.com/vi/SeVIyZaY_C0/mqdefault.jpg",
                "width": 320,
                "height": 180
            },
            "high": {
                "url": "https://i.ytimg.com/vi/SeVIyZaY_C0/hqdefault.jpg",
                "width": 480,
                "height": 360
            },
            "standard": {
                "url": "https://i.ytimg.com/vi/SeVIyZaY_C0/sddefault.jpg",
                "width": 640,
                "height": 480
            },
            "maxres": {
                "url": "https://i.ytimg.com/vi/SeVIyZaY_C0/maxresdefault.jpg",
                "width": 1280,
                "height": 720
            }
        },
        "channelTitle": "Cyrus Yip",
        "playlistId": "PLRct1-5In-8Ewg5Kq-0JP8wh3ZweOXH9A",
        "resourceId": {
            "kind": "youtube#video",
            "videoId": "SeVIyZaY_C0"
        },
        "videoOwnerChannelTitle": "[PIAS]",
        "videoOwnerChannelId": "UC1SdL_M0CUZyRsFzyHcy76A"
    },
    "contentDetails": {
        "videoId": "SeVIyZaY_C0",
        "videoPublishedAt": "2017-09-05T10:36:47Z",
        "duration": "PT4M14S",
        "dimension": "2d",
        "definition": "hd",
        "caption": "false",
        "licensedContent": true,
        "contentRating": {},
        "projection": "rectangular"
    },
    "status": {
        "privacyStatus": "public"
    },
    "statistics": {
        "viewCount": "243397",
        "likeCount": "4506",
        "favoriteCount": "0",
        "commentCount": "387"
    }
}