{
    "kind": "youtube#playlistItem",
    "id": "UExSY3QxLTVJbi04RXdnNUtxLTBKUDh3aDNad2VPWEg5QS44QUNDQ0M1NDkwQTY0OUMw",
    "snippet": {
        "publishedAt": "2022-02-04T05:36:34Z",
        "channelId": "UCX5XEfoxcLU9Dr_GVIdsLPA",
        "title": "Mike Posner - I Took A Pill In Ibiza (SeeB Remix)",
        "description": "Mike Posner - I Took A Pill In Ibiza (SeeB Remix)\n\ud83d\udd25 STREAM NOW: https://trapnation.komi.io\n\nMike Posner\n\u2717\u00a0https://soundcloud.com/mikeposner\n\u2717\u00a0http://twitter.com/MikePosner\n\n\u2717 Copyright Free Music (Safe to Use - No Copyright Claim): https://broke.ffm.to/downloadbroke\n\n#artistname #tracktitle #chillnation #chill #edm #chillmusic #chillremix #remix #music #mix #visualizer",
        "thumbnails": {
            "default": {
                "url": "https://i.ytimg.com/vi/u3VFzuUiTGw/default.jpg",
                "width": 120,
                "height": 90
            },
            "medium": {
                "url": "https://i.ytimg.com/vi/u3VFzuUiTGw/mqdefault.jpg",
                "width": 320,
                "height": 180
            },
            "high": {
                "url": "https://i.ytimg.com/vi/u3VFzuUiTGw/hqdefault.jpg",
                "width": 480,
                "height": 360
            },
            "standard": {
                "url": "https://i.ytimg.com/vi/u3VFzuUiTGw/sddefault.jpg",
                "width": 640,
                "height": 480
            },
            "maxres": {
                "url": "https://i.ytimg.com/vi/u3VFzuUiTGw/maxresdefault.jpg",
                "width": 1280,
                "height": 720
            }
        },
        "channelTitle": "Cyrus Yip",
        "playlistId": "PLRct1-5In-8Ewg5Kq-0JP8wh3ZweOXH9A",
        "resourceId": {
            "kind": "youtube#video",
            "videoId": "u3VFzuUiTGw"
        },
        "videoOwnerChannelTitle": "Chill Nation",
        "videoOwnerChannelId": "UCM9KEEuzacwVlkt9JfJad7g"
    },
    "contentDetails": {
        "videoId": "u3VFzuUiTGw",
        "videoPublishedAt": "2016-02-03T18:00:02Z",
        "duration": "PT3M20S",
        "dimension": "2d",
        "definition": "hd",
        "caption": "false",
        "licensedContent": false,
        "contentRating": {},
        "projection": "rectangular"
    },
    "status": {
        "privacyStatus": "public"
    },
    "statistics": {
        "viewCount": "130910438",
        "likeCount": "793615",
        "favoriteCount": "0",
        "commentCount": "15280"
    }
}