{
    "kind": "youtube#playlistItem",
    "id": "UExSY3QxLTVJbi04RXdnNUtxLTBKUDh3aDNad2VPWEg5QS43NUVCRUMxQjU0MkM5QjI2",
    "snippet": {
        "publishedAt": "2022-06-26T03:23:07Z",
        "channelId": "UCX5XEfoxcLU9Dr_GVIdsLPA",
        "title": "Cloudy June - Mommy Issues (Official Music Video)",
        "description": "Stream 'Mommy Issues' here: https://sng.to/cloudyjune/mommy-issues\n\n_____________________________________________________________\nWE'RE ALL MAD HERE TOUR 2024: Tickets - https://tix.to/Cloudy\n\n03/06 Birmingham, UK\n03/07 Manchester, UK\n03/08 Leeds, UK\n03,09 London, UK,\n03/12 Amsterdam, NL\n03/13 Antwerpen, BEL\n03/14 Paris, FR\n03/20 Zurich, CHE\n03/21 Stuttgart, GER\n03/22 Frankfurt, GER\n03/24 Munich, GER\n03/25 Vienna, AUT\n03/26 Prague, CZE\n03/28 Warsaw, POL\n04/03 Cologne, GER\n04/04 Hamburg, GER\n05/05 Berlin, GER\n\nSupported by Initiative Musik GmbH with project funds from the Federal Government Commissioner for Culture and Media.\n\nEditor: Niko Gindler, Cloudy June\n\nDirector/DOP: Niko Gindler\nhttps://www.instagram.com/nik_motionstills/\n\nMake-Up: Antina Christ \nhttps://www.instagram.com/antina_christ/",
        "thumbnails": {
            "default": {
                "url": "https://i.ytimg.com/vi/vLkb8V5gHy4/default.jpg",
                "width": 120,
                "height": 90
            },
            "medium": {
                "url": "https://i.ytimg.com/vi/vLkb8V5gHy4/mqdefault.jpg",
                "width": 320,
                "height": 180
            },
            "high": {
                "url": "https://i.ytimg.com/vi/vLkb8V5gHy4/hqdefault.jpg",
                "width": 480,
                "height": 360
            },
            "standard": {
                "url": "https://i.ytimg.com/vi/vLkb8V5gHy4/sddefault.jpg",
                "width": 640,
                "height": 480
            },
            "maxres": {
                "url": "https://i.ytimg.com/vi/vLkb8V5gHy4/maxresdefault.jpg",
                "width": 1280,
                "height": 720
            }
        },
        "channelTitle": "Cyrus Yip",
        "playlistId": "PLRct1-5In-8Ewg5Kq-0JP8wh3ZweOXH9A",
        "resourceId": {
            "kind": "youtube#video",
            "videoId": "vLkb8V5gHy4"
        },
        "videoOwnerChannelTitle": "Cloudy June",
        "videoOwnerChannelId": "UCa6U7jauahu2nPdI54j_9wA"
    },
    "contentDetails": {
        "videoId": "vLkb8V5gHy4",
        "videoPublishedAt": "2022-03-21T09:00:58Z",
        "duration": "PT2M55S",
        "dimension": "2d",
        "definition": "hd",
        "caption": "false",
        "licensedContent": true,
        "contentRating": {},
        "projection": "rectangular"
    },
    "status": {
        "privacyStatus": "public"
    },
    "statistics": {
        "viewCount": "2387779",
        "likeCount": "58783",
        "favoriteCount": "0",
        "commentCount": "409"
    }
}