{
    "kind": "youtube#playlistItem",
    "id": "UExSY3QxLTVJbi04RXdnNUtxLTBKUDh3aDNad2VPWEg5QS42ODFGN0E1QzU1RjJEMTNE",
    "snippet": {
        "publishedAt": "2021-10-01T04:06:59Z",
        "channelId": "UCX5XEfoxcLU9Dr_GVIdsLPA",
        "title": "O-Zone - Dragostea Din Tei [Official Video]",
        "description": "O-Zone - Dragostea Din Tei [Official Video]\niTunes: https://itunes.apple.com/it/album/dragostea-din-tei/1295665938\nSpotify: https://open.spotify.com/album/5KJRYCxiahHmBjZkzY4HzL\n\n\"Dragostea Din Tei\" \u00e8 una della tante hit della dance band moldava O-Zone. La loro storia \u00e8 cominciata nella Repubblica Moldava, dove Dan, Arsenie e Radu hanno conosciuto i loro primi successi musicali. In questo modo si sono convinti che la musica pop rumena poteva essere interessante x quanto riguarda il mercato europeo e potevano esserci i presupposti per l'inizio di una carriera Internazionale. Ecco perch\u00e9 nel 2002 gli O-Zone hanno dato un loro demo a Dan Popi un manager di un'etichetta discografica rumena nel quale hanno riposto la loro fiducia. Il loro primo singolo in Romania \u00e8 stato: \"Numai Tu\" tratto dal loro album \"Number 1\". Numai Tu ha conquistato le classifiche radio e la Top 100 rumena. Nell'autunno 2002 gli O-zone tornano con un nuovo singolo \"Despre Tine\" e le nuove stelle della musica dance si accorgono di aver contaminato sia le radio sia le televisioni della Romania con \"l'O-Zone Mania\".\n\n\"Dragostea Din Tei\" by O-Zone was one of the most played singles by the Italian radio stations and reached NR 1 in all the European sales charts: Nr 1 in France for 15 weeks (Platinum Record), Nr 1 in Spain, Nr 1 in Germany (Platinum Record), Nr 3 in the UK, Nr 1 in Belgium (Platinum Record), Nr 1 in Holland (Platinum Record), Nr 1 in Norway (Platinum Record in 2 week), Nr 1 in Austria, Switzerland and in all the Eastern European Countries (...)\n\nLike us on Facebook: http://facebook.com/timerec\nSubscribe to TimeRecTv!!! http://bit.ly/2fVwESX\nTime HEAVY ROTATION on Youtube: http://goo.gl/N2b511\nTime HEAVY ROTATION on Spotify: https://goo.gl/bkK2G0\n\nGet TIME RADIO on the app stores!!!\niOS: http://goo.gl/MmiV7J / Android: http://goo.gl/1diB9Q\nBlackBerry: http://goo.gl/9A478L\n\nFOLLOW US! Stay Connected:\nhttp://facebook.com/timerec\nhttp://www.timerec.it\nhttp://twitter.com/TimeRecordsIta\nhttp://google.com/+TimeRecords\nhttp://spoti.fi/13h6Dju\nhttp://instagram.com/timerecordsofficial\nhttp://www.tsu.co/TIMERECORDS\nhttp://www.soundcloud.com/timerec\n\n#ozone #dragosteadintei #timerecords",
        "thumbnails": {
            "default": {
                "url": "https://i.ytimg.com/vi/YnopHCL1Jk8/default.jpg",
                "width": 120,
                "height": 90
            },
            "medium": {
                "url": "https://i.ytimg.com/vi/YnopHCL1Jk8/mqdefault.jpg",
                "width": 320,
                "height": 180
            },
            "high": {
                "url": "https://i.ytimg.com/vi/YnopHCL1Jk8/hqdefault.jpg",
                "width": 480,
                "height": 360
            },
            "standard": {
                "url": "https://i.ytimg.com/vi/YnopHCL1Jk8/sddefault.jpg",
                "width": 640,
                "height": 480
            },
            "maxres": {
                "url": "https://i.ytimg.com/vi/YnopHCL1Jk8/maxresdefault.jpg",
                "width": 1280,
                "height": 720
            }
        },
        "channelTitle": "Cyrus Yip",
        "playlistId": "PLRct1-5In-8Ewg5Kq-0JP8wh3ZweOXH9A",
        "resourceId": {
            "kind": "youtube#video",
            "videoId": "YnopHCL1Jk8"
        },
        "videoOwnerChannelTitle": "Time Records",
        "videoOwnerChannelId": "UCWOom9E_zqXS0VdWW949WUA"
    },
    "contentDetails": {
        "videoId": "YnopHCL1Jk8",
        "videoPublishedAt": "2011-07-13T19:53:07Z",
        "duration": "PT4M46S",
        "dimension": "2d",
        "definition": "hd",
        "caption": "false",
        "licensedContent": false,
        "contentRating": {},
        "projection": "rectangular"
    },
    "status": {
        "privacyStatus": "public"
    },
    "statistics": {
        "viewCount": "160353708",
        "likeCount": "1774714",
        "favoriteCount": "0",
        "commentCount": "109103"
    }
}