{
    "kind": "youtube#playlistItem",
    "id": "UExSY3QxLTVJbi04RXdnNUtxLTBKUDh3aDNad2VPWEg5QS45NEQxMDc1RDMxNUJDMzQy",
    "snippet": {
        "publishedAt": "2022-04-27T04:31:37Z",
        "channelId": "UCX5XEfoxcLU9Dr_GVIdsLPA",
        "title": "Pharrell Williams - Happy (Video)",
        "description": "Official Music Video for \"Happy\" by Pharrell Williams\nListen to Pharrell: https://PharrellWilliams.lnk.to/listenYD\n\nSubscribe to the official Pharrell YouTube channel: https://PharrellWilliams.lnk.to/subscribeYD\n\nWatch more Pharrell videos: https://PharrellWilliams.lnk.to/listenYC/youtube\n\nFollow Pharrell:\nFacebook: https://PharrellWilliams.lnk.to/followFI\nInstagram: https://PharrellWilliams.lnk.to/followII\nTwitter: https://PharrellWilliams.lnk.to/followTI\nWebsite: https://PharrellWilliams.lnk.to/followWI\nSpotify: https://PharrellWilliams.lnk.to/followSI\nYouTube: https://PharrellWilliams.lnk.to/subscribeYD\n\nChorus:\n(Because I'm happy)\nClap along if you feel like a room without a roof\n(Because I'm happy)\nClap along if you feel like happiness is the truth\n(Because I'm happy)\nClap along if you know what happiness is to you\n(Because I'm happy)\nClap along if you feel like that's what you wanna do\n\n#PharrellWilliams #Happy #GIRL",
        "thumbnails": {
            "default": {
                "url": "https://i.ytimg.com/vi/ZbZSe6N_BXs/default.jpg",
                "width": 120,
                "height": 90
            },
            "medium": {
                "url": "https://i.ytimg.com/vi/ZbZSe6N_BXs/mqdefault.jpg",
                "width": 320,
                "height": 180
            },
            "high": {
                "url": "https://i.ytimg.com/vi/ZbZSe6N_BXs/hqdefault.jpg",
                "width": 480,
                "height": 360
            },
            "standard": {
                "url": "https://i.ytimg.com/vi/ZbZSe6N_BXs/sddefault.jpg",
                "width": 640,
                "height": 480
            },
            "maxres": {
                "url": "https://i.ytimg.com/vi/ZbZSe6N_BXs/maxresdefault.jpg",
                "width": 1280,
                "height": 720
            }
        },
        "channelTitle": "Cyrus Yip",
        "playlistId": "PLRct1-5In-8Ewg5Kq-0JP8wh3ZweOXH9A",
        "resourceId": {
            "kind": "youtube#video",
            "videoId": "ZbZSe6N_BXs"
        },
        "videoOwnerChannelTitle": "PharrellWilliamsVEVO",
        "videoOwnerChannelId": "UCtQMmwBJGvINGU0lZ_GrZKQ"
    },
    "contentDetails": {
        "videoId": "ZbZSe6N_BXs",
        "videoPublishedAt": "2014-01-08T08:00:01Z",
        "duration": "PT4M1S",
        "dimension": "2d",
        "definition": "hd",
        "caption": "true",
        "licensedContent": true,
        "contentRating": {},
        "projection": "rectangular"
    },
    "status": {
        "privacyStatus": "public"
    },
    "statistics": {
        "viewCount": "1312305643",
        "likeCount": "8677649",
        "favoriteCount": "0",
        "commentCount": "234689"
    }
}